{
  "Name": "Dansk", 

  // Kuriimu2 Main GUI texts
  "File": "Fil",
  "Tools": "Værktøj",
  "Ciphers": "Kodesprog",
  "Compressions": "Sammenpresse",
  "Settings": "Opsætning",

  "Open": "Åben",
  "OpenWith": "Åben med...",
  "Save": "Gemme",
  "SaveAs": "Gemme som...",
  "SaveAll": "Gemme Alting",
  "Close": "Lukke",

  "TextSequenceSearcher": "Tekst Søgen",
  "BatchExtractor": "Ekstrakt Alting",
  "BatchInjector": "Erstatte Alting",

  "Hashes": "Hash",

  "Encrypt": "Kryptere",
  "Decrypt": "Dekode",

  "Decompress": "Dekomprimere",
  "Compress": "komprimere",

  "RawImageViewer": "Se rå Images",

  "IncludeDevBuilds": "Udvikler Opbygge",
  "ChangeLanguage": "Udskifte Sprog",
  "ChangeLanguageCaption": "Alle ændre vilje afspejle sig efter genstarte.",
  "ChangeLanguageTitle": "Ændre Indstilling",

  "Help": "Hjælp",
  "AboutKuriimu2": "Angående Kuriimu2",

  "LoadErrorCaption": "Loade Fejl",
  "SaveErrorCaption": "Lagre Fejl",
  "UnsavedChangesCaption": "Ikke lagre ændre",
  "DependantFilesCaption": "Afhængig filer",
  "ExceptionCatchedCaption": "Undtagelse kaste",
  "UnhandledExceptionCaption": "Ubehandlet undtagelse",
  "UpdateAvailableCaption": "Opdatering lettilgængelig",
  "PluginsNotAvailableCaption": "Tilslutte ikke tilgængelig",

  "LoadCancelledStatus": "Loade aflyst.",
  "NoPluginSelectedStatus": "Intet tilslutte udsøgt.",
  "NoFileSelectedStatus": "Intet fil udsøgt.",
  "FileAlreadyOpeningStatus": "{0} være allerede åbnings",
  "FileAlreadySavingStatus": "{0} være allerede lagring.",
  "FileSuccessfullyLoaded": "Fil belæsset succesfuldt.",
  "FileNotSuccessfullyLoaded": "Fil behøve belæsset succesfuldt.",
  "FileNotSuccessfullyLoadedWithPlugin": "Fil behøve belæsset succesfuldt med tilslutte {0}.",
  "FileSavedSuccessfullyStatus": "Fil lagre succesfuldt.",
  "FileNotSavedSuccessfullyStatus": "Fil behøve lagre succesfuldt.",
  "OperationsStillRunningStatus": "Operationer er stadig igang, og fil må ikke lukkes.",

  "SelectedFileInvalid": "Den valgte fil er ugyldig.",
  "UnsavedChangesToFile": "Der er foretaget ændringer ved {0} eller dens åbnede subfiler. Ønsker du at gemme disse ændringer?",
  "UnsavedChangesGeneric": "Der er foretaget ændringer ved en eller flere filer. Ønsker du at gemme disse ændringer?",
  "DependantFiles": "Alle fil, der er åbnet fra denne fil og derefter, vil også blive lukket. Fortsætte?",
  "UnhandledExceptionCloseApp": "Der opstod en ubehandlet undtagelse. Se loggen for at få flere oplysninger. Applikationen vil blive lukket.",
  "UnhandledExceptionNotCloseApp": "Der opstod en ubehandlet undtagelse. Se loggen for at få flere oplysninger.",
  "UpdateAvailable": "Ønsker du at opdatere fra {0}-{1} til {2}-{3}?",
  "FollowingPluginsNotLoaded": "Følgende tilslutte kunne ikke blive belæsset",

  "AllFilesFilter": "Alle Dokumenter",

  "UnsupportedOperatingSystemException": "Operativsystem, der ikke understøttes: {0}.",
  "UnsupportedPlatformException": "Unsupported Platform: {0}.",

  // Kuriimu2 Archive Form
  "ClearSearch": "Fjerne",
  "CancelOperation": "Aflyse",

  "Extract": "Ekstrakt",
  "Replace": "Erstatte",
  "Rename": "Omdøbe",
  "Delete": "Slette",
  "Add": "Tilføje",

  "ExtractFile": "Ekstrakt fil(er)",
  "ReplaceFile": "Erstatte fil(er)",
  "RenameFile": "Omdøbe fil",
  "DeleteFile": "Silette fil",

  "FileName": "Navn",
  "FileSize": "Størrelse",

  "NoTargetSelectedStatus": "Der blev ikke valgt noget mål.",

  "NoFilesToExtractStatus": "Ingen filer til ekstrakt.",
  "NoFilesToReplaceStatus": "Ingen filer til erstatte.",
  "NoFilesToRenameStatus": "Ingen filer til omdøbe.",
  "NoFilesToDeleteStatus": "Ingen filer til slette.",
  "NoFilesToAddStatus": "Ingen filer til tilsætte.",

  "ExtractFileProgress": "Ekstrakt filer",
  "ReplaceFileProgress": "Erstatte filer",
  "RenameFileProgress": "Omdøbe filer",
  "DeleteFileProgress": "Slette filer",
  "AddFileProgress": "Tilsætte filer",

  "ExtractFileCancelledStatus": "Fil udvinding aflyse.",
  "ReplaceFileCancelledStatus": "Fil erstatning aflyse.",
  "RenameFileCancelledStatus": "Fil omdøbe aflyse.",
  "DeleteFileCancelledStatus": "Fil strygning aflyse.",
  "AddFileCancelledStatus": "Fil tilsætte aflyse.",

  "ExtractFileSuccessfulStatus": "Fil(er) ekstrakt succesfuldt.",
  "ReplaceFileSuccessfulStatus": "Fil(er) erstatte succesfuldt.",
  "RenameFileSuccessfulStatus": "Fil(er) omdøbe succesfuldt.",
  "DeleteFileSuccessfulStatus": "Fil(er) slette succesfuldt.",
  "AddFileSuccessfulStatus": "Fil(er) tilsætte succesfuldt.",

  "UnableToAddFilesStatus": "Nogle filer kunne ikke tilføjes. Se loggen for at få flere oplysninger.",

  "NoNameGivenStatus": "Der gives ikke noget nyt navn.",

  "RenameFileTitle": "Omdøbe fil",
  "RenameDirectoryTitle": "Omdøbe mappe",

  "RenameItemCaption": "Vælge et ny navn til {0}:",

  // Kuriimu2 Image form
  "ExportImage": "Eksport billede",
  "ImportImage": "Importere billede",

  "Width": "Bredde:",
  "Height": "Højde:",
  "Format": "Format:",
  "Palette": "Palet:",

  "ExportPngTitle": "Eksport PNG...",
  "ImportPngTitle": "Importere PNG...",

  "ImageSuccessfullyImportedStatus": "Billede succesrig importere.",

  "PngFileFilter": "Bærbar Netværksgrafik (*.png)",

  // Kuriimu2 Text Sequence Searcher
  "TextSequenceSearcherTitle": "Tekst Rækkefølge Søger",
  "SearchSubfolders": "Søgning Undermappe",

  "Find": "Finde",
  "FindIn": "Finde ind:",
  "FindWhat": "Finde hvad:",
  "Browse": "Surfe...",
  "Encoding": "Kryptere:",

  "SelectSearchDirectory": "Vælg den mappe, der skal søges i",

  "SelectEncodingCaption": "Vælg en Kryptere.",
  "SelectSearchDirectoryCaption": "Vælg den mappe, der skal søges i.",
  "SelectSearchTextCaption": "Vælg en tekst, du vil søge efter.",

  // Kuriimu2 ChoosePluginDialog
  "ChooseOpenFilePlugin": "Vælg tilslutte til at åbne filen med:",
  "MultiplePluginMatchesSelection": "Flere tilslutte kan identificere denne fil. Vælg venligst en:",
  "NonIdentifiablePluginSelection": "Kunne ikke automatisk bestemme tilslutte til åbning af denne fil, vælg venligst manuelt:",
  "NonIdentifiablePluginSelectionNote": "Som standard vises kun tilslutter, der ikke automatisk kunne bestemme, om de understøtter filen, som standard",

  "PluginNameColumn": "Navn",
  "PluginTypeColumn": "Type",
  "PluginDescriptionColumn": "Beskrivelse",
  "PluginIdColumn": "GUID",

  "ChoosePluginTitle": "Vælge tilslutte",
  "ChoosePluginContinue": "Fortsætte",
  "ChoosePluginRawBytes": "Vis rå bytes",
  "ChoosePluginCancel": "Annuller",
  "ChoosePluginShowAll": "Vis alle tilslutter",

  // Kuriimu2 DialogManager
  "CancelDialog": "Dialogen blev annulleret.",
  "UnsupportedDialogFieldType": "Ikke understøttet dialogfelt af typen {0}.",
  "DialogOkButton": "Ok",

  // Kuriimu2 InputBox
  "InputBoxOkButton": "Ok",

  // Kuriimu2 RawImageViewer
  "NoSwizzle": "Ingen",
  "CustomSwizzle": "Skrædder",

  "ComponentOrder": "Bestilling Rækkefølge",
  "ByteOrder": "Byte Rækkefølge",
  "BitOrder": "Stykke Rækkefølge",
  "ZOrder": "Z-Rækkefølge",
  "AlphaLuminance": "Alfa/Lysstyrke",
  "AlphaMode": "Alfa Modus",
  "SwizzleMode": "Swizzle Modus",
  "BitMapping": "Bit-Tilknytning",
  "InitPoint": "InitPoint",
  "YTransform": "Y Omforme",

  "InvalidInputValuesStatus": "Indtastede værdier er ugyldige.",
  "InvalidCustomSwizzleStatus": "Brugerdefineret swizzle er ugyldig.",

  "SelectedFileNotExistStatus": "Den valgte fil findes ikke.",

  "RawImageViewerEncodingParameters": "Kryptere Parameters",
  "RawImageViewerEncodingPaletteParameters": "Kryptere Palet Parameters",
  "RawImageViewerSwizzleParameters": "Swizzle Parameters",

  "Offset": "Modregne:",
  "PaletteOffset": "Palet Modregne:",
  "Swizzle": "Swizzle:",

  "Process": "Fremgangsmåde",

  // Kuriimu2 BatchDialog
  "AvgTimePerFile": "Gennemsnitlig tid pr. fil:",
  "AvgTimePerFileTimed": "Gennemsnitlig tid pr. fil: {0}ms",

  "BatchAvailablePlugins": "Tilslutte",
  "BatchSelectInput": "Udsøgt input...",
  "BatchSelectOutput": "Udsøgt output...",
  "Execute": "Udføre",

  "BatchSelectPluginStatus": "Udsøgt en tilslutte.",

  "BatchExtractSourceEmpty": "Udsøgt en mappe med filer, der skal udpakkes.",
  "BatchExtractDestinationEmpty": "Udsøgt en mappe til at udpakke filerne til.",

  "BatchInjectSourceEmpty": "Udsøgt en mappe med filer, der skal injiceres.",
  "BatchInjectDestinationEmpty": "Udsøgt en mappe med mapper til at injicere til filerne.",

  // Kuriimu2 Extension Dialogs
  "ExtensionParameters": "Parameters",
  "AutoExecute": "Automatisk udførelse ved udvælgelse",

  "SelectFolder": "Udsøgt mappe...",
  "SelectFile": "Udsøgt fil...",

  "Compression": "Komprimering",
  "Decompression": "Dekomprimering",
  "Encryption": "Kryptering",
  "Decryption": "Dekryptering",

  "SelectTypeExtension": "Udsøgt en {0}.",
  "SelectFileOrFolder": "Udsøgt en fil eller mappe, der skal behandles.",
  "FileFailed": "{0} Fejlslået: {1}",
  "ProcessFinishedCaption": "Resultaterne skrives til {0}.",
  "ProcessFinishedTitle": "Færdig!",
  "CipherNotSupported": "Uopfyldelig chiffer {0}.",
  "CompressionNotSupported": "Uopfyldelig chiffer {0}."
}